ascend_deployer/__init__.py
ascend_deployer/ansible.cfg
ascend_deployer/ascend_deployer.py
ascend_deployer/ascend_download.py
ascend_deployer/downloader_ui.py
ascend_deployer/install.sh
ascend_deployer/inventory_file
ascend_deployer/jobs.py
ascend_deployer/start_download.sh
ascend_deployer/start_download_ui.bat
ascend_deployer/utils.py
ascend_deployer/version.json
ascend_deployer/ansible_plugin/ansible_log.py
ascend_deployer/ansible_plugin/install_info.yaml
ascend_deployer/downloader/__init__.py
ascend_deployer/downloader/config.ini
ascend_deployer/downloader/deb_downloader.py
ascend_deployer/downloader/dl_mef_dependency_downloader.py
ascend_deployer/downloader/download_data.py
ascend_deployer/downloader/download_util.py
ascend_deployer/downloader/downloader.py
ascend_deployer/downloader/logger_config.py
ascend_deployer/downloader/obs_downloader.py
ascend_deployer/downloader/obs_resources.json
ascend_deployer/downloader/os_dep_downloader.py
ascend_deployer/downloader/other_downloader.py
ascend_deployer/downloader/other_resources.json
ascend_deployer/downloader/parallel_file_downloader.py
ascend_deployer/downloader/pip_downloader.py
ascend_deployer/downloader/python_version.json
ascend_deployer/downloader/requirements.txt
ascend_deployer/downloader/rpm_downloader.py
ascend_deployer/downloader/software_mgr.py
ascend_deployer/downloader/version_match.json
ascend_deployer/downloader/config/BCLinux_21.10_aarch64/pkg_info.json
ascend_deployer/downloader/config/BCLinux_21.10_aarch64/source.repo
ascend_deployer/downloader/config/CTyunOS_22.06_aarch64/installed.txt
ascend_deployer/downloader/config/CTyunOS_22.06_aarch64/pkg_info.json
ascend_deployer/downloader/config/CTyunOS_22.06_aarch64/source.repo
ascend_deployer/downloader/config/CTyunOS_22.06_x86_64/installed.txt
ascend_deployer/downloader/config/CTyunOS_22.06_x86_64/pkg_info.json
ascend_deployer/downloader/config/CTyunOS_22.06_x86_64/source.repo
ascend_deployer/downloader/config/CentOS_7.6_aarch64/pkg_info.json
ascend_deployer-5.0.6.dist-info/LICENSE
ascend_deployer-5.0.6.dist-info/METADATA
ascend_deployer-5.0.6.dist-info/NOTICE
ascend_deployer-5.0.6.dist-info/WHEEL
ascend_deployer-5.0.6.dist-info/entry_points.txt
ascend_deployer-5.0.6.dist-info/top_level.txt
ascend_deployer-5.0.6.dist-info/RECORD
