Metadata-Version: 2.1
Name: ascend-deployer
Version: 5.0.6
Summary: ascend offline installer
Home-page: https://gitee.com/ascend/ascend-deployer
License: Apache
Classifier: Programming Language :: Python :: 3
Classifier: License :: OSI Approved :: Apache Software License
Classifier: Operating System :: OS Independent
Requires-Python: >= 3.6
License-File: LICENSE
License-File: NOTICE
